django_webhook_subscriber/__init__.py
django_webhook_subscriber/admin.py
django_webhook_subscriber/apps.py
django_webhook_subscriber/conf.py
django_webhook_subscriber/delivery.py
django_webhook_subscriber/http.py
django_webhook_subscriber/managers.py
django_webhook_subscriber/models.py
django_webhook_subscriber/serializers.py
django_webhook_subscriber/tasks.py
django_webhook_subscriber/utils.py
django_webhook_subscriber/validators.py
django_webhook_subscriber/management/__init__.py
django_webhook_subscriber/management/commands/__init__.py
django_webhook_subscriber/management/commands/webhook.py
django_webhook_subscriber/management/commands/webhook_cache.py
django_webhook_subscriber/management/commands/webhook_logs.py
django_webhook_subscriber/management/commands/webhook_performance_test.py
django_webhook_subscriber/management/commands/webhook_send.py
django_webhook_subscriber/management/commands/webhook_status.py
django_webhook_subscriber/migrations/0001_initial.py
django_webhook_subscriber/migrations/0002_remove_webhookregistry_content_type_and_more.py
django_webhook_subscriber/migrations/__init__.py
django_webhook_subscriber/tests/__init__.py
django_webhook_subscriber/tests/factories.py
django_webhook_subscriber/tests/settings.py
django_webhook_subscriber/tests/test_delivery.py
django_webhook_subscriber/tests/test_http.py
django_webhook_subscriber/tests/test_managers.py
django_webhook_subscriber/tests/test_models.py
django_webhook_subscriber/tests/test_serializers.py
django_webhook_subscriber/tests/test_tasks.py
django_webhook_subscriber/tests/test_utils.py
django_webhook_subscriber-2.0.0.dist-info/licenses/LICENSE
django_webhook_subscriber-2.0.0.dist-info/METADATA
django_webhook_subscriber-2.0.0.dist-info/WHEEL
django_webhook_subscriber-2.0.0.dist-info/top_level.txt
django_webhook_subscriber-2.0.0.dist-info/RECORD
