Metadata-Version: 2.4
Name: django-webhook-subscriber
Version: 2.0.0
Summary: A Django package designed to handle webhook creation, management, and delivery.
Author-email: 42 Portugal <root@42porto.com>
Classifier: Environment :: Web Environment
Classifier: Framework :: Django
Classifier: Framework :: Django :: 5.0
Classifier: Intended Audience :: Developers
Classifier: License :: OSI Approved :: BSD License
Classifier: Operating System :: OS Independent
Classifier: Programming Language :: Python
Classifier: Programming Language :: Python :: 3
Classifier: Programming Language :: Python :: 3 :: Only
Classifier: Programming Language :: Python :: 3.10
Classifier: Programming Language :: Python :: 3.11
Classifier: Programming Language :: Python :: 3.12
Classifier: Programming Language :: Python :: 3.13
Classifier: Topic :: Internet :: WWW/HTTP
Classifier: Topic :: Internet :: WWW/HTTP :: Dynamic Content
Requires-Python: >=3.10
License-File: LICENSE
Requires-Dist: Django<5.3,>=5.0
Requires-Dist: djangorestframework<3.17,>=3.15.0
Requires-Dist: requests<2.33,>=2.32.3
Requires-Dist: celery<5.6,>=5.0.0
Requires-Dist: redis<6.5,>=6.4
Provides-Extra: test
Requires-Dist: pytest<8.4,>=8.3.4; extra == "test"
Requires-Dist: pytest-django<5.0,>=4.9.0; extra == "test"
Requires-Dist: pytest-cov<6.1,>=6.0.0; extra == "test"
Requires-Dist: pytest-factoryboy<2.9,>=2.8; extra == "test"
Dynamic: license-file
